whatodo-0.1.0a4.dist-info/top_level.txt
whatodo-0.1.0a4.dist-info/entry_points.txt
whatodo-0.1.0a4.dist-info/WHEEL
whatodo-0.1.0a4.dist-info/DESCRIPTION.rst
whatodo-0.1.0a4.dist-info/metadata.json
whatodo-0.1.0a4.dist-info/METADATA
whatodo-0.1.0a4.dist-info/RECORD
src/__main__.py
src/todo.py
src/test_main.py
src/__init__.py
src/main.py
src/test_todo.py
src/__pycache__/__init__.cpython-34.pyc
src/__pycache__/test_todo.cpython-34-PYTEST.pyc
